LICENSE
MANIFEST.in
README.md
package.json
setup.py
url_observer/UrlObserver.py
url_observer/__init__.py
url_observer/_imports_.py
url_observer/metadata.json
url_observer/package-info.json
url_observer/url_observer.min.js
url_observer/url_observer.min.js.map
url_observer.egg-info/PKG-INFO
url_observer.egg-info/SOURCES.txt
url_observer.egg-info/dependency_links.txt
url_observer.egg-info/top_level.txt