Metadata-Version: 2.1
Name: url-observer
Version: 1.0.5
Summary: Project Description
Author: s_matsumoto <s_matsumoto@thinkup-sol.co.jp>
License: MIT
Classifier: Framework :: Dash
License-File: LICENSE
